README.md
setup.cfg
setup.py
SpaGoG.egg-info/PKG-INFO
SpaGoG.egg-info/SOURCES.txt
SpaGoG.egg-info/dependency_links.txt
SpaGoG.egg-info/requires.txt
SpaGoG.egg-info/top_level.txt
spagog/__init__.py
spagog/experiments.py
spagog/main.py
spagog/datasets/__init__.py
spagog/datasets/graphDataPair.py
spagog/datasets/graphDataset.py
spagog/datasets/graphsDataPair.py
spagog/datasets/graphsDataset.py
spagog/datasets/tabDataPair.py
spagog/datasets/tabDataset.py
spagog/models/__init__.py
spagog/models/abstractModel.py
spagog/models/abstractNN.py
spagog/models/graphClassification.py
spagog/models/graphNodeClassification.py
spagog/models/nodeClassification.py
spagog/utils/__init__.py
spagog/utils/gfp.py
spagog/utils/knn.py
spagog/utils/data/__init__.py
spagog/utils/data/tab2graph.py
spagog/utils/metrics/__init__.py
spagog/utils/metrics/metrics.py