Metadata-Version: 1.1
Name: SpaGoG
Version: 0.12
Summary: Sparse data classification using Graph of Graphs models
Home-page: https://github.com/HananyaS/SpaGoG
Author: Shachar Hananya
Author-email: shacharhananya@gmail.com
License: MIT
Download-URL: https://github.com/HananyaS/SpaGoG/archive/refs/tags/v_0.12.tar.gz
Keywords: GoG
Platform: UNKNOWN
